[{"name": "84 athletes", "match_count": 2}, {"name": "AIM Academy", "match_count": 3}, {"name": "Adams State", "match_count": 148}, {"name": "Adrian", "match_count": 27}, {"name": "Air Force", "match_count": 2545}, {"name": "Air Force Academy Preparatory School", "match_count": 8}, {"name": "Air Force Prep", "match_count": 19}, {"name": "AirForce Prep", "match_count": 1}, {"name": "Akron Club", "match_count": 1}, {"name": "Albany", "match_count": 2}, {"name": "Albion", "match_count": 16}, {"name": "Alderson Broaddus", "match_count": 12}, {"name": "Alfred State", "match_count": 21}, {"name": "Allen", "match_count": 17}, {"name": "Allen University", "match_count": 1}, {"name": "Alma", "match_count": 11}, {"name": "Alma College", "match_count": 12}, {"name": "Alvernia University", "match_count": 40}, {"name": "American", "match_count": 2017}, {"name": "American International", "match_count": 20}, {"name": "Ancilla College", "match_count": 4}, {"name": "Andrew College", "match_count": 21}, {"name": "Anibals Animals", "match_count": 5}, {"name": "Appalachian State", "match_count": 2767}, {"name": "Apprentice School", "match_count": 52}, {"name": "Archbold", "match_count": 1}, {"name": "Arizona Christian University", "match_count": 18}, {"name": "Arizona State", "match_count": 1642}, {"name": "Arkansas RTC", "match_count": 2}, {"name": "Army Prep", "match_count": 111}, {"name": "Army Prep - UNATT", "match_count": 17}, {"name": "Army Prep - UnAttached", "match_count": 11}, {"name": "Army West Point", "match_count": 3415}, {"name": "Ashland", "match_count": 163}, {"name": "Augsburg", "match_count": 102}, {"name": "Augustana (IL)", "match_count": 11}, {"name": "Augustana (SD)", "match_count": 162}, {"name": "Aurora Universtiy", "match_count": 12}, {"name": "Averett", "match_count": 18}, {"name": "Avila", "match_count": 31}, {"name": "BYU", "match_count": 6}, {"name": "Backyard Bullies WC", "match_count": 1}, {"name": "Baker (Kan.)", "match_count": 33}, {"name": "Baldwin Wallace", "match_count": 20}, {"name": "Barton", "match_count": 16}, {"name": "Basement Brawlers", "match_count": 1}, {"name": "Bear Cave Wrestling", "match_count": 1}, {"name": "Bears Regional Training Center", "match_count": 13}, {"name": "Beat the Streets LA Oxnard", "match_count": 1}, {"name": "Beat the streets", "match_count": 4}, {"name": "Beaver Dam RTC", "match_count": 6}, {"name": "Bellarmine", "match_count": 2408}, {"name": "Belmont Abbey", "match_count": 59}, {"name": "Benedictine College", "match_count": 13}, {"name": "Bergen Community College", "match_count": 5}, {"name": "Bethany (Kan.)", "match_count": 1}, {"name": "Betterman Elite", "match_count": 1}, {"name": "Big Bend", "match_count": 5}, {"name": "Big Bend Community College", "match_count": 21}, {"name": "Binghamton", "match_count": 2143}, {"name": "Bismarck State CC", "match_count": 3}, {"name": "Bismarck State College", "match_count": 9}, {"name": "Blackburn", "match_count": 5}, {"name": "Blackfoot", "match_count": 1}, {"name": "Blackfox Wrestling Academy", "match_count": 1}, {"name": "Blair Academy", "match_count": 4}, {"name": "Blair Academy - Post Grad", "match_count": 20}, {"name": "Blair Wrestling", "match_count": 5}, {"name": "Blairstown Wrestling Club - UNATT", "match_count": 4}, {"name": "Bloomsburg", "match_count": 1819}, {"name": "Blue and Gold RTC", "match_count": 2}, {"name": "Bluefield College", "match_count": 1}, {"name": "Bluefield State", "match_count": 47}, {"name": "Bluff City Wrestling", "match_count": 1}, {"name": "Boom Ranch - UNATT", "match_count": 7}, {"name": "Brewton-Parker (GA)", "match_count": 37}, {"name": "Briar Cliff (Iowa)", "match_count": 19}, {"name": "Bridgeport", "match_count": 11}, {"name": "Brockport", "match_count": 29}, {"name": "Brookville", "match_count": 1}, {"name": "Brown", "match_count": 1635}, {"name": "Brtc", "match_count": 2}, {"name": "Bryant & Stratton", "match_count": 4}, {"name": "Bryant & Stratton College", "match_count": 10}, {"name": "Bucknell", "match_count": 2138}, {"name": "Bucknell-Unattached", "match_count": 4}, {"name": "Buena Vista", "match_count": 9}, {"name": "Buffalo", "match_count": 2376}, {"name": "Bull Combat RTC", "match_count": 3}, {"name": "Bull Trained Wrestling", "match_count": 3}, {"name": "Bull trained", "match_count": 2}, {"name": "Bulltrained", "match_count": 1}, {"name": "Burnett Trained Wrestling", "match_count": 3}, {"name": "CDM Wrestling Club", "match_count": 1}, {"name": "CSU Bakersfield", "match_count": 1422}, {"name": "CSU-Pueblo", "match_count": 107}, {"name": "CWC", "match_count": 4}, {"name": "Cal Poly", "match_count": 1632}, {"name": "Cal Poly Humboldt", "match_count": 111}, {"name": "California Baptist", "match_count": 1584}, {"name": "Camden County College", "match_count": 23}, {"name": "Camp Reynolds Wrestling Club", "match_count": 1}, {"name": "Campbell", "match_count": 2059}, {"name": "Campbellsville (Ky.)", "match_count": 51}, {"name": "Carl Albert State", "match_count": 54}, {"name": "Carolina Takedown Club", "match_count": 3}, {"name": "Carthage College", "match_count": 11}, {"name": "Case Western Reserve", "match_count": 18}, {"name": "Castleton", "match_count": 5}, {"name": "Cavalier Wrestling Club", "match_count": 2}, {"name": "Cavalier Wrestling club", "match_count": 2}, {"name": "Cavalier wrestling club", "match_count": 2}, {"name": "Cedarville", "match_count": 1}, {"name": "Centenary (NJ)", "match_count": 87}, {"name": "Central", "match_count": 14}, {"name": "Central Baptist (Ark.)", "match_count": 16}, {"name": "Central Christian College (KS)", "match_count": 4}, {"name": "Central FL Wrestling", "match_count": 1}, {"name": "Central Methodist", "match_count": 44}, {"name": "Central Michigan", "match_count": 2631}, {"name": "Central Missouri", "match_count": 184}, {"name": "Central Oklahoma", "match_count": 131}, {"name": "Cerritos (W)", "match_count": 1}, {"name": "Chadron State", "match_count": 87}, {"name": "Chattanooga", "match_count": 1859}, {"name": "Chicago", "match_count": 16}, {"name": "Cincinnati Club", "match_count": 1}, {"name": "Clackamas Community College", "match_count": 123}, {"name": "Clackamas Unattached", "match_count": 2}, {"name": "Clarion", "match_count": 1788}, {"name": "Cleary University", "match_count": 18}, {"name": "Clemson", "match_count": 3}, {"name": "Cleveland State", "match_count": 1273}, {"name": "Cliff Keen Wrestling Club", "match_count": 1}, {"name": "Cloud County Community College", "match_count": 26}, {"name": "Clt Rtc", "match_count": 1}, {"name": "Coach quit", "match_count": 1}, {"name": "Coast Guard", "match_count": 3}, {"name": "Coe", "match_count": 16}, {"name": "Coker", "match_count": 24}, {"name": "Colby Community College", "match_count": 26}, {"name": "College of the Redwoods", "match_count": 6}, {"name": "Colorado Mesa", "match_count": 211}, {"name": "Colorado Northwestern CC", "match_count": 6}, {"name": "Colorado School of Mines", "match_count": 113}, {"name": "Colorado State", "match_count": 8}, {"name": "Colorado State Univeristy", "match_count": 1}, {"name": "Colorado State University", "match_count": 11}, {"name": "Colorado State University Club", "match_count": 1}, {"name": "Colorado State University Wrestling Club", "match_count": 2}, {"name": "Columbia", "match_count": 2416}, {"name": "Columbia RTC", "match_count": 5}, {"name": "Combat WC", "match_count": 2}, {"name": "Concordia (Neb.)", "match_count": 53}, {"name": "Concordia-Moorhead", "match_count": 40}, {"name": "Corban University", "match_count": 61}, {"name": "Cornell", "match_count": 2020}, {"name": "Cornell College", "match_count": 27}, {"name": "Cornerstone", "match_count": 16}, {"name": "Cortland State", "match_count": 9}, {"name": "Cougar WC", "match_count": 9}, {"name": "Cougar Wrestling Club", "match_count": 2}, {"name": "Cowley College", "match_count": 11}, {"name": "Creek RTC", "match_count": 1}, {"name": "Cuesta", "match_count": 5}, {"name": "Cumberland (Tenn.)", "match_count": 75}, {"name": "Cumberlands (Ky.)", "match_count": 86}, {"name": "Cyclone Wrestling Club", "match_count": 2}, {"name": "Dakota Wesleyan (S.D.)", "match_count": 20}, {"name": "Davenport", "match_count": 53}, {"name": "Davidson", "match_count": 1776}, {"name": "Davis & Elkins", "match_count": 5}, {"name": "Defiance College", "match_count": 3}, {"name": "Delaware Valley", "match_count": 13}, {"name": "Dickinson State (N.D.)", "match_count": 17}, {"name": "Diplomat Wrestling Club", "match_count": 2}, {"name": "Doane University", "match_count": 21}, {"name": "Dog Pound", "match_count": 3}, {"name": "Douglas College", "match_count": 1}, {"name": "Drexel", "match_count": 2485}, {"name": "Drury", "match_count": 87}, {"name": "Dubuque", "match_count": 14}, {"name": "Duke", "match_count": 1401}, {"name": "E3", "match_count": 1}, {"name": "EAP", "match_count": 11}, {"name": "EAP OTC", "match_count": 2}, {"name": "EAP Program", "match_count": 2}, {"name": "EC Old Guys", "match_count": 7}, {"name": "ETC", "match_count": 3}, {"name": "EWU - Unattached", "match_count": 1}, {"name": "Eap-unatt", "match_count": 8}, {"name": "East Stroudsburg", "match_count": 109}, {"name": "Eastern", "match_count": 3}, {"name": "Eastern Oregon University (OR)", "match_count": 91}, {"name": "Edge Wrestling (Hoboken)", "match_count": 1}, {"name": "Edinboro", "match_count": 2671}, {"name": "Edinboro Unattached", "match_count": 20}, {"name": "Elevate", "match_count": 1}, {"name": "Elite Wrestling", "match_count": 2}, {"name": "Elizabethtown", "match_count": 10}, {"name": "Ellsworth CC", "match_count": 14}, {"name": "Elmhurst University", "match_count": 3}, {"name": "Elmira College", "match_count": 8}, {"name": "Embry Riddle Aeronautical University", "match_count": 2}, {"name": "Embry-Riddle (Ariz.)", "match_count": 156}, {"name": "Emmanuel", "match_count": 78}, {"name": "Emmanuel College", "match_count": 5}, {"name": "Emory & Henry", "match_count": 9}, {"name": "Emory & Henry College", "match_count": 10}, {"name": "Eureka", "match_count": 22}, {"name": "Evergreen State College", "match_count": 19}, {"name": "Eyes n The Prize", "match_count": 4}, {"name": "FGCU", "match_count": 1}, {"name": "Fairmont State", "match_count": 48}, {"name": "Felician", "match_count": 55}, {"name": "Ferris State University", "match_count": 8}, {"name": "Ferrum", "match_count": 8}, {"name": "Findlay", "match_count": 205}, {"name": "First Flight", "match_count": 3}, {"name": "Florey Farms", "match_count": 3}, {"name": "Florida A&M University", "match_count": 2}, {"name": "Florida Gulf Coast University", "match_count": 1}, {"name": "Florida State", "match_count": 1}, {"name": "Fontbonne", "match_count": 16}, {"name": "Fort Hays State", "match_count": 106}, {"name": "Fort Hays Tech Northwest", "match_count": 33}, {"name": "Fort dodge", "match_count": 2}, {"name": "Franklin & Marshall", "match_count": 2918}, {"name": "Fresno (Club)", "match_count": 1}, {"name": "Friends University", "match_count": 21}, {"name": "Funky Monkey", "match_count": 9}, {"name": "G3", "match_count": 1}, {"name": "GPSW", "match_count": 1}, {"name": "GTA Alliance WC", "match_count": 5}, {"name": "GWU-Unattached", "match_count": 1}, {"name": "Gannon", "match_count": 323}, {"name": "Gardner-Webb", "match_count": 2030}, {"name": "Garrett College", "match_count": 24}, {"name": "George Mason", "match_count": 2157}, {"name": "Georgetown (KY)", "match_count": 6}, {"name": "Georgia Tech Wrestling Club", "match_count": 1}, {"name": "Gettysburg", "match_count": 25}, {"name": "Gfa", "match_count": 5}, {"name": "Glenville State", "match_count": 93}, {"name": "Glenville State College", "match_count": 37}, {"name": "Glenville State University", "match_count": 38}, {"name": "Gold Rush Wrestling", "match_count": 4}, {"name": "Gopher Wrestling Club", "match_count": 2}, {"name": "Gopher Wrestling Club (GWC)", "match_count": 4}, {"name": "Graceland University", "match_count": 36}, {"name": "Grand Canyon University", "match_count": 2}, {"name": "Grand Valley State", "match_count": 324}, {"name": "Grand Valley State University Wrestling Club", "match_count": 39}, {"name": "Grand View (Iowa)", "match_count": 557}, {"name": "Great Neck Wrestling Club", "match_count": 1}, {"name": "Green Farms Academy", "match_count": 2}, {"name": "Greens Farms Academy", "match_count": 3}, {"name": "Greensboro", "match_count": 127}, {"name": "Grit Mat Club", "match_count": 1}, {"name": "Ground Zero Wrestling Club", "match_count": 2}, {"name": "Guru Gobind Singh WC", "match_count": 1}, {"name": "Gus? Garage", "match_count": 1}, {"name": "Gym-O", "match_count": 3}, {"name": "Hacc Hawks", "match_count": 3}, {"name": "Harper College", "match_count": 37}, {"name": "Harvard", "match_count": 1552}, {"name": "Hastings (Neb.)", "match_count": 10}, {"name": "Hawkeye Community College", "match_count": 1}, {"name": "Hecox Team Benaiah", "match_count": 2}, {"name": "Heidelberg", "match_count": 10}, {"name": "Henry Ford College", "match_count": 17}, {"name": "Hillsdale College", "match_count": 2}, {"name": "Hofstra", "match_count": 2010}, {"name": "Hope International University", "match_count": 18}, {"name": "Hunter", "match_count": 13}, {"name": "Huntingdon", "match_count": 27}, {"name": "Ichiban Wrestling Club", "match_count": 1}, {"name": "Icon Wrestling", "match_count": 1}, {"name": "Illinois", "match_count": 1867}, {"name": "Impact Wrestling Academy", "match_count": 2}, {"name": "Independence", "match_count": 1}, {"name": "Independent", "match_count": 3}, {"name": "Indian Hill Community College", "match_count": 114}, {"name": "Indiana", "match_count": 2321}, {"name": "Indiana State Club", "match_count": 2}, {"name": "Indiana Tech", "match_count": 117}, {"name": "Indianapolis", "match_count": 220}, {"name": "Integrity Wrestling Club", "match_count": 4}, {"name": "Iowa", "match_count": 2120}, {"name": "Iowa Central", "match_count": 2}, {"name": "Iowa Central Community College", "match_count": 113}, {"name": "Iowa Lakes Community College", "match_count": 15}, {"name": "Iowa State", "match_count": 2701}, {"name": "Iowa State Club", "match_count": 1}, {"name": "Iowa State Wrestling Club", "match_count": 14}, {"name": "Iowa Wesleyan", "match_count": 2}, {"name": "Iowa Western Community College", "match_count": 52}, {"name": "IronClad", "match_count": 1}, {"name": "Ithaca", "match_count": 53}, {"name": "JWU - Unattached", "match_count": 1}, {"name": "Jackrabbit Wrestling Club", "match_count": 26}, {"name": "James Madison University", "match_count": 3}, {"name": "Jamestown (N.D.)", "match_count": 11}, {"name": "Jamestown Community College", "match_count": 9}, {"name": "Jarvis Christian College", "match_count": 11}, {"name": "John Carroll", "match_count": 80}, {"name": "Johns Hopkins", "match_count": 12}, {"name": "Johnson & Wales (RI)", "match_count": 28}, {"name": "Joliet Junior College", "match_count": 17}, {"name": "Kean", "match_count": 2}, {"name": "Keiser University", "match_count": 42}, {"name": "Kennesaw Mountain", "match_count": 1}, {"name": "Kent State", "match_count": 2627}, {"name": "Kentucky Wesleyan", "match_count": 61}, {"name": "King", "match_count": 86}, {"name": "King University", "match_count": 10}, {"name": "King`s (PA)", "match_count": 32}, {"name": "Knights RTC", "match_count": 1}, {"name": "Kutztown", "match_count": 78}, {"name": "LIU", "match_count": 1256}, {"name": "Labette Community College", "match_count": 43}, {"name": "Lackawanna College", "match_count": 16}, {"name": "Lake Erie", "match_count": 201}, {"name": "Lakeland", "match_count": 2}, {"name": "Lander", "match_count": 130}, {"name": "Lasalle", "match_count": 1}, {"name": "Lassen College", "match_count": 2}, {"name": "Lehigh", "match_count": 2469}, {"name": "Lemoore College", "match_count": 3}, {"name": "Liberty", "match_count": 51}, {"name": "Liberty Christian Academy - UNATT", "match_count": 6}, {"name": "Life University", "match_count": 266}, {"name": "Limestone", "match_count": 69}, {"name": "Lincoln Memorial", "match_count": 3}, {"name": "Lindenwood", "match_count": 294}, {"name": "Lindenwood (Mo.)", "match_count": 62}, {"name": "Lindsey Wilson (Ky.)", "match_count": 29}, {"name": "Linfield", "match_count": 4}, {"name": "Linfield University", "match_count": 16}, {"name": "Little Rock", "match_count": 1942}, {"name": "Lock Haven", "match_count": 3037}, {"name": "Lorain", "match_count": 2}, {"name": "Loras", "match_count": 82}, {"name": "Lourdes University", "match_count": 12}, {"name": "Luther", "match_count": 60}, {"name": "Lycoming", "match_count": 7}, {"name": "Lyon College", "match_count": 1}, {"name": "M2", "match_count": 2}, {"name": "M2NJ", "match_count": 3}, {"name": "MF Wrestling", "match_count": 2}, {"name": "Maine Maritime Academy", "match_count": 2}, {"name": "Maine Maritme Academy", "match_count": 3}, {"name": "Malvern Prep", "match_count": 2}, {"name": "Manchester", "match_count": 74}, {"name": "Marauder - Unattached", "match_count": 1}, {"name": "Marian University (IN)", "match_count": 108}, {"name": "Marian University - Ancilla", "match_count": 9}, {"name": "Marlow Outlaws Wrestling", "match_count": 2}, {"name": "Mary", "match_count": 12}, {"name": "Maryland", "match_count": 2133}, {"name": "Marymount", "match_count": 120}, {"name": "Maryville", "match_count": 219}, {"name": "Massachusetts Institute of Technology", "match_count": 2}, {"name": "Mat Assassins", "match_count": 3}, {"name": "Mauldin", "match_count": 2}, {"name": "Mavericks Wrestling", "match_count": 1}, {"name": "Mayo Quanchi", "match_count": 1}, {"name": "McDaniel", "match_count": 2}, {"name": "McKendree", "match_count": 228}, {"name": "Menlo (Calif.)", "match_count": 281}, {"name": "Menlo NCWA", "match_count": 8}, {"name": "Mentor High", "match_count": 2}, {"name": "Merchant Marine", "match_count": 24}, {"name": "Mercyhurst", "match_count": 173}, {"name": "Mercyhurst NorthEast", "match_count": 5}, {"name": "Messiah", "match_count": 72}, {"name": "Miami Club Wrestling", "match_count": 1}, {"name": "Michigan", "match_count": 2017}, {"name": "Michigan State", "match_count": 2532}, {"name": "Michigsn State", "match_count": 1}, {"name": "Middlesex Community College", "match_count": 4}, {"name": "Midland (Neb.)", "match_count": 27}, {"name": "Midway University", "match_count": 15}, {"name": "Millersville", "match_count": 352}, {"name": "Minion Training Center", "match_count": 3}, {"name": "Minions Wrestling Club", "match_count": 1}, {"name": "Minnesota", "match_count": 2206}, {"name": "Minnesota North - Itasca", "match_count": 13}, {"name": "Minnesota State", "match_count": 63}, {"name": "Minnesota State Mankato", "match_count": 8}, {"name": "Minnesota State Moorhead", "match_count": 47}, {"name": "Minnesota West Comm & Tech", "match_count": 6}, {"name": "Minot State (N.D.)", "match_count": 36}, {"name": "Misericordia", "match_count": 16}, {"name": "Missouri", "match_count": 2561}, {"name": "Missouri Baptist University", "match_count": 46}, {"name": "Missouri Valley", "match_count": 112}, {"name": "Monmouth", "match_count": 2}, {"name": "Monmouth University", "match_count": 5}, {"name": "Monroeville", "match_count": 1}, {"name": "Montana State-Northern", "match_count": 77}, {"name": "Montevallo", "match_count": 32}, {"name": "Montreat College", "match_count": 36}, {"name": "Morgan State", "match_count": 1001}, {"name": "Morningside (Iowa)", "match_count": 26}, {"name": "Morton College", "match_count": 13}, {"name": "Mott Community College", "match_count": 11}, {"name": "Mount Olive", "match_count": 42}, {"name": "Mount St. Joseph", "match_count": 16}, {"name": "Mount Union", "match_count": 38}, {"name": "Mt San Antonio Community College", "match_count": 6}, {"name": "Muddawg Wrestling Club", "match_count": 1}, {"name": "Muhlenberg", "match_count": 19}, {"name": "Murray State", "match_count": 2}, {"name": "Muskegon Community College", "match_count": 16}, {"name": "Muskingum", "match_count": 2}, {"name": "Muz Trained", "match_count": 1}, {"name": "N/A", "match_count": 3}, {"name": "N/a", "match_count": 2}, {"name": "NAPS", "match_count": 26}, {"name": "NC State", "match_count": 2113}, {"name": "NC United", "match_count": 5}, {"name": "NC Wrestling Factory", "match_count": 3}, {"name": "NCWA - Ohio State University", "match_count": 2}, {"name": "NJRTC", "match_count": 11}, {"name": "NJRTC - UnAttached", "match_count": 10}, {"name": "NR-PRTC", "match_count": 12}, {"name": "NYAC", "match_count": 3}, {"name": "NYC RTC - UNATT", "match_count": 4}, {"name": "NYCRTC", "match_count": 9}, {"name": "NYCRTC Unattached", "match_count": 2}, {"name": "NYMA-Unatt", "match_count": 4}, {"name": "NYRTC", "match_count": 1}, {"name": "NYU", "match_count": 37}, {"name": "Naps", "match_count": 10}, {"name": "Nassau Community College", "match_count": 160}, {"name": "Naumen", "match_count": 1}, {"name": "Naval Acadamy Prep", "match_count": 4}, {"name": "Naval Academy Prep School", "match_count": 60}, {"name": "Navy", "match_count": 2633}, {"name": "Navy Academy Prep School", "match_count": 5}, {"name": "Navy Prep", "match_count": 16}, {"name": "Navy Wrestling Club", "match_count": 4}, {"name": "Navy Wrestling Club - UnAttached", "match_count": 2}, {"name": "Nebraska", "match_count": 2300}, {"name": "Nebraska Wesleyan", "match_count": 11}, {"name": "Nebraska-Kearney", "match_count": 219}, {"name": "Neosho County Community College", "match_count": 7}, {"name": "New England College", "match_count": 5}, {"name": "New England RTC", "match_count": 3}, {"name": "New Jersey City University", "match_count": 30}, {"name": "New Mexico Highlands", "match_count": 89}, {"name": "New River Wrestling Club", "match_count": 2}, {"name": "New York City Regional Training Center", "match_count": 13}, {"name": "New York Military", "match_count": 9}, {"name": "New York Military Academy", "match_count": 6}, {"name": "New York Military Academy/ West Point Wrestling Cl", "match_count": 2}, {"name": "Newberry", "match_count": 179}, {"name": "Newman", "match_count": 39}, {"name": "Niagara Community College", "match_count": 21}, {"name": "No Team", "match_count": 1}, {"name": "NoWorries Academy", "match_count": 3}, {"name": "Noke Wrestling RTC", "match_count": 63}, {"name": "Noke Wrestling RTC - UNAFF", "match_count": 2}, {"name": "Norfolk Academy - UNATT", "match_count": 2}, {"name": "North Carolina", "match_count": 2355}, {"name": "North Central", "match_count": 41}, {"name": "North Dakota State", "match_count": 2119}, {"name": "North Idaho College", "match_count": 37}, {"name": "North Iowa Area Community College", "match_count": 11}, {"name": "Northampton Community College", "match_count": 6}, {"name": "Northeast Oklahoma", "match_count": 123}, {"name": "Northeastern Junior College", "match_count": 66}, {"name": "Northeastern Oklahoma A&M", "match_count": 6}, {"name": "Northeastern University", "match_count": 2}, {"name": "Northern Colorado", "match_count": 1728}, {"name": "Northern Illinois", "match_count": 1989}, {"name": "Northern Iowa", "match_count": 2438}, {"name": "Northern Kentucky University", "match_count": 1}, {"name": "Northern Oklahoma College-Tonkawa", "match_count": 6}, {"name": "Northern State", "match_count": 128}, {"name": "Northfield Mt. Hermon", "match_count": 4}, {"name": "Northland Community & Technical College", "match_count": 18}, {"name": "Northwest College", "match_count": 11}, {"name": "Northwest Kansas Technical College", "match_count": 67}, {"name": "Northwestern", "match_count": 1641}, {"name": "Northwestern (Iowa)", "match_count": 14}, {"name": "Northwestern University", "match_count": 1}, {"name": "Norwich", "match_count": 2}, {"name": "Notre Dame (Ohio)", "match_count": 23}, {"name": "Notre Dame Green Pond", "match_count": 1}, {"name": "Nycrtc", "match_count": 7}, {"name": "Nyma", "match_count": 3}, {"name": "Ohio", "match_count": 2205}, {"name": "Ohio Northern", "match_count": 37}, {"name": "Ohio State", "match_count": 2432}, {"name": "Ohio Valley Christian Community College", "match_count": 2}, {"name": "Ohio Wesleyan", "match_count": 9}, {"name": "Oklahoma", "match_count": 1836}, {"name": "Oklahoma City", "match_count": 32}, {"name": "Oklahoma St", "match_count": 5}, {"name": "Oklahoma State", "match_count": 2059}, {"name": "Oklahoma Wesleyan", "match_count": 18}, {"name": "Olivet", "match_count": 46}, {"name": "Olympic", "match_count": 1}, {"name": "Omega Training Center", "match_count": 8}, {"name": "One Unit Wrestling Academy", "match_count": 2}, {"name": "Oneonta State", "match_count": 23}, {"name": "Onondaga Community College", "match_count": 17}, {"name": "Open", "match_count": 7}, {"name": "Orchard", "match_count": 2}, {"name": "Oregon State", "match_count": 2312}, {"name": "Oswego State", "match_count": 19}, {"name": "Otero Junior College", "match_count": 23}, {"name": "Ottawa", "match_count": 9}, {"name": "Ottawa University", "match_count": 35}, {"name": "Otterbein University", "match_count": 10}, {"name": "Ouachita Baptist", "match_count": 47}, {"name": "PRTC", "match_count": 99}, {"name": "Pacific (OR)", "match_count": 17}, {"name": "Pacific Lutheran University, WA", "match_count": 1}, {"name": "Palomar College", "match_count": 5}, {"name": "Panther Creek", "match_count": 2}, {"name": "Paradigm Wrestling", "match_count": 1}, {"name": "Patrick Henry Community College", "match_count": 2}, {"name": "Peddie", "match_count": 2}, {"name": "Peddie School", "match_count": 4}, {"name": "Penn", "match_count": 359}, {"name": "Penn RTC", "match_count": 19}, {"name": "Penn State", "match_count": 1782}, {"name": "Penn State Behrend", "match_count": 4}, {"name": "Penn state Altoona", "match_count": 1}, {"name": "Pennsylvania", "match_count": 1919}, {"name": "Pennsylvania College of Technology", "match_count": 53}, {"name": "Pennsylvania RTC", "match_count": 43}, {"name": "Pennsylvania State University", "match_count": 8}, {"name": "Pennsylvania State University - Altoona", "match_count": 8}, {"name": "Peterson Grapplers", "match_count": 3}, {"name": "Pikeville", "match_count": 9}, {"name": "Pitt-Bradford", "match_count": 13}, {"name": "Pitt-Johnstown", "match_count": 285}, {"name": "Pittsburgh", "match_count": 2009}, {"name": "Point Park", "match_count": 23}, {"name": "Ponderosa", "match_count": 3}, {"name": "Pratt Community College", "match_count": 31}, {"name": "Presbyterian", "match_count": 449}, {"name": "Presbyterian College", "match_count": 491}, {"name": "Princeton", "match_count": 1826}, {"name": "Providence (Mont.)", "match_count": 48}, {"name": "Prtc", "match_count": 83}, {"name": "Punisher wrestling club", "match_count": 10}, {"name": "Purdue", "match_count": 2091}, {"name": "Queens", "match_count": 272}, {"name": "Quincy", "match_count": 109}, {"name": "RAW", "match_count": 1}, {"name": "RIT", "match_count": 21}, {"name": "Ranger Wrestling Club", "match_count": 1}, {"name": "Rednose", "match_count": 2}, {"name": "Reinhardt University (GA)", "match_count": 59}, {"name": "Rensselaer Polytechnic Institute", "match_count": 13}, {"name": "Reynolds", "match_count": 1}, {"name": "Rhode Island College", "match_count": 26}, {"name": "Rider", "match_count": 2133}, {"name": "Ridgewater College", "match_count": 7}, {"name": "Rio Hondo College", "match_count": 9}, {"name": "Rising Sun Wrestling Club", "match_count": 2}, {"name": "Roanoke College", "match_count": 183}, {"name": "Rochester Christian University", "match_count": 7}, {"name": "Rochester Community & Tech. College", "match_count": 58}, {"name": "Rochester University", "match_count": 48}, {"name": "Roger Williams", "match_count": 6}, {"name": "Roundtree Wrestling Academy", "match_count": 2}, {"name": "RoundtreeNess", "match_count": 3}, {"name": "Rowan College of South Jersey", "match_count": 8}, {"name": "Rpw", "match_count": 2}, {"name": "Rustom WC", "match_count": 1}, {"name": "Rutgers", "match_count": 2465}, {"name": "S.A.W.", "match_count": 4}, {"name": "SERTC- unattached", "match_count": 3}, {"name": "SERTC-VT", "match_count": 10}, {"name": "SIRTC", "match_count": 3}, {"name": "SIU Edwardsville", "match_count": 2248}, {"name": "SKWC", "match_count": 2}, {"name": "SUNY Sullivan", "match_count": 2}, {"name": "SUNY Ulster", "match_count": 3}, {"name": "Sacramento City College", "match_count": 17}, {"name": "Sacramento State", "match_count": 1}, {"name": "Sacramento State University", "match_count": 6}, {"name": "Sacred Heart", "match_count": 1313}, {"name": "Salem", "match_count": 15}, {"name": "San Francisco State", "match_count": 192}, {"name": "San Joaquin Delta College", "match_count": 2}, {"name": "Sauquoit", "match_count": 1}, {"name": "Savage University", "match_count": 3}, {"name": "Scarlet Knight Wrest;ing Club", "match_count": 2}, {"name": "Schreiner", "match_count": 28}, {"name": "Scotsman WC - UNAFF", "match_count": 2}, {"name": "Scranton", "match_count": 14}, {"name": "Seagull Wrestling Club", "match_count": 1}, {"name": "Seasons WC", "match_count": 2}, {"name": "Seton Hill", "match_count": 95}, {"name": "Shade Tree RTC", "match_count": 3}, {"name": "Shark-Style Wrestling", "match_count": 4}, {"name": "Shasta Community College", "match_count": 4}, {"name": "Shenandoah University", "match_count": 11}, {"name": "Shippensburg", "match_count": 13}, {"name": "Shorter (Ga.)", "match_count": 4}, {"name": "Siena Heights University", "match_count": 19}, {"name": "Sierra College", "match_count": 11}, {"name": "Silver Back", "match_count": 2}, {"name": "Simon Fraser", "match_count": 6}, {"name": "Simon Fraser (B.C.)", "match_count": 50}, {"name": "Simpson", "match_count": 7}, {"name": "Simpson (Calif.)", "match_count": 25}, {"name": "Sioux Falls", "match_count": 23}, {"name": "Skyline College", "match_count": 7}, {"name": "Slippery Rock Universtiy", "match_count": 3}, {"name": "Snow", "match_count": 40}, {"name": "Sons of Thunder Academy", "match_count": 1}, {"name": "Souderton", "match_count": 1}, {"name": "South Dakota State", "match_count": 2710}, {"name": "South Georgia Athletic Club", "match_count": 2}, {"name": "Southeast Community College", "match_count": 67}, {"name": "Southeast RTC - UNATT", "match_count": 6}, {"name": "Southeast Regional Training Center", "match_count": 6}, {"name": "Southeastern", "match_count": 161}, {"name": "Southeastern Community College", "match_count": 1}, {"name": "Southern Maine", "match_count": 2}, {"name": "Southern Oregon", "match_count": 155}, {"name": "Southern Virginia", "match_count": 10}, {"name": "Southwest Minnesota State", "match_count": 26}, {"name": "Southwest Virginia Community College", "match_count": 2}, {"name": "Southwestern Michigan", "match_count": 49}, {"name": "Southwestern Oregon Community College", "match_count": 26}, {"name": "Spartan Combat RTC", "match_count": 438}, {"name": "Spartan Combat RTC - UNATT", "match_count": 36}, {"name": "Spartan Elite", "match_count": 2}, {"name": "Spartan RTC", "match_count": 15}, {"name": "Spartan Wrestling Club - UnAttached", "match_count": 21}, {"name": "Spider", "match_count": 2}, {"name": "Spire Academy", "match_count": 28}, {"name": "Springfield", "match_count": 3}, {"name": "Springfield Technical Community College", "match_count": 6}, {"name": "St. Ambrose University", "match_count": 60}, {"name": "St. Andrews University", "match_count": 28}, {"name": "St. Benedicts Prep", "match_count": 1}, {"name": "St. Clair Community College", "match_count": 9}, {"name": "St. Cloud State", "match_count": 187}, {"name": "St. Johns (MN)", "match_count": 13}, {"name": "St. Joseph Regional", "match_count": 2}, {"name": "St. Peter&apos;s Prep", "match_count": 1}, {"name": "St. Thomas University", "match_count": 12}, {"name": "St. Vincent College", "match_count": 8}, {"name": "Stanford", "match_count": 1509}, {"name": "Steller Trained", "match_count": 3}, {"name": "Stevens", "match_count": 6}, {"name": "Stevens Tech", "match_count": 29}, {"name": "Stronghold", "match_count": 8}, {"name": "Sussex County Community College", "match_count": 39}, {"name": "Syracuse Club", "match_count": 2}, {"name": "TCNJ", "match_count": 64}, {"name": "TNWA", "match_count": 1}, {"name": "Tar Heel Wrestling Club", "match_count": 3}, {"name": "Tarleton State", "match_count": 87}, {"name": "Team Cabo Verde", "match_count": 1}, {"name": "Team Miron", "match_count": 2}, {"name": "Team Stronghold", "match_count": 4}, {"name": "Temple club", "match_count": 5}, {"name": "Tennessee Valley Wrestling", "match_count": 2}, {"name": "Texas Wesleyan", "match_count": 24}, {"name": "Thaddeus Stevens College Of Tech.", "match_count": 13}, {"name": "The Apprentice School", "match_count": 12}, {"name": "The Citadel", "match_count": 2252}, {"name": "The Compound", "match_count": 2}, {"name": "The Compound RTC", "match_count": 2}, {"name": "The Hill School", "match_count": 9}, {"name": "The Storm Wrestling Center", "match_count": 1}, {"name": "Thiel", "match_count": 2}, {"name": "Thomas More", "match_count": 46}, {"name": "Three Clowns", "match_count": 1}, {"name": "Tiffin", "match_count": 185}, {"name": "Toledo", "match_count": 27}, {"name": "Treasure Valley CC", "match_count": 2}, {"name": "Treasure Valley Community College", "match_count": 2}, {"name": "Trine", "match_count": 34}, {"name": "Trinidad State", "match_count": 15}, {"name": "Triton College", "match_count": 55}, {"name": "Truett-McConnell (Ga.)", "match_count": 71}, {"name": "UCF", "match_count": 1}, {"name": "UConn university", "match_count": 1}, {"name": "UGA", "match_count": 1}, {"name": "UIndy", "match_count": 20}, {"name": "UMASS", "match_count": 4}, {"name": "UMBC", "match_count": 4}, {"name": "UMD Club Wrestling", "match_count": 1}, {"name": "UMary", "match_count": 70}, {"name": "UNA - Angry Peach", "match_count": 1}, {"name": "UNA-C2X Academy", "match_count": 1}, {"name": "UNA-Charleston RTC", "match_count": 3}, {"name": "UNA-Compound", "match_count": 2}, {"name": "UNA-Cuncil Rck Nrth", "match_count": 1}, {"name": "UNA-Darkhorse", "match_count": 4}, {"name": "UNA-Frieza force UNCP", "match_count": 2}, {"name": "UNA-Gym-O University", "match_count": 3}, {"name": "UNA-Raw", "match_count": 2}, {"name": "UNA-Sunkist Kids", "match_count": 2}, {"name": "UNA-Swain county WC", "match_count": 2}, {"name": "UNA-Tarheel wrestling club", "match_count": 5}, {"name": "UNA-Triumph Wrestling", "match_count": 2}, {"name": "UNA-Un Rostered", "match_count": 3}, {"name": "UNA-Unaffiliated", "match_count": 1}, {"name": "UNA-Unattached", "match_count": 10}, {"name": "UNAFF", "match_count": 21}, {"name": "UNAFFILIATED - COLLEGE", "match_count": 42}, {"name": "UNAFFILIATED - HS", "match_count": 24}, {"name": "UNAT", "match_count": 2}, {"name": "UNATT", "match_count": 46}, {"name": "UNATT - Peddie", "match_count": 1}, {"name": "UNATT - Unattached", "match_count": 15}, {"name": "UNATT-Binghamton", "match_count": 1}, {"name": "UNATT-Blair Wrestling", "match_count": 1}, {"name": "UNATT-Bucknell", "match_count": 1}, {"name": "UNATT-Davidson", "match_count": 16}, {"name": "UNATT-Duke", "match_count": 1}, {"name": "UNATT-George Mason", "match_count": 16}, {"name": "UNATT-Green Farms Academy", "match_count": 5}, {"name": "UNATT-Harrisburg Area CC Wrestling Club Team", "match_count": 1}, {"name": "UNATT-Lake Highland Prep", "match_count": 1}, {"name": "UNATT-Lock Haven", "match_count": 12}, {"name": "UNATT-Marymount University", "match_count": 1}, {"name": "UNATT-Mat Assassins", "match_count": 2}, {"name": "UNATT-Michigan State", "match_count": 10}, {"name": "UNATT-NC State", "match_count": 5}, {"name": "UNATT-Naval Academy Prep School", "match_count": 5}, {"name": "UNATT-Nevada Reno", "match_count": 1}, {"name": "UNATT-Noke Wrestling RTC", "match_count": 2}, {"name": "UNATT-Northfield Mt. Hermon", "match_count": 3}, {"name": "UNATT-Pursuit", "match_count": 1}, {"name": "UNATT-The Hill School", "match_count": 3}, {"name": "UNATT-USMAPS/Army Prep", "match_count": 1}, {"name": "UNATT-Unattached", "match_count": 1}, {"name": "UNATT-Unknown", "match_count": 1}, {"name": "UNATT-Unrostered", "match_count": 15}, {"name": "UNATT-Wilkes", "match_count": 7}, {"name": "UNATT-Wyoming Seminary", "match_count": 6}, {"name": "UNATT-Yale Street", "match_count": 4}, {"name": "UNATT-individual", "match_count": 6}, {"name": "UNATTACHED", "match_count": 30}, {"name": "UNC", "match_count": 37}, {"name": "UNC Pembroke", "match_count": 190}, {"name": "UNH", "match_count": 196}, {"name": "UPJ", "match_count": 7}, {"name": "USAFA Prep", "match_count": 15}, {"name": "USMAPS", "match_count": 48}, {"name": "USMAPS (Army Prep)", "match_count": 24}, {"name": "USMAPS/Army Prep", "match_count": 92}, {"name": "USMC", "match_count": 1}, {"name": "USO PTC / EAP-UNA", "match_count": 1}, {"name": "UTC - Unattached", "match_count": 7}, {"name": "UVA", "match_count": 1}, {"name": "UW-Eau Claire", "match_count": 10}, {"name": "UWL", "match_count": 4}, {"name": "Uconn club", "match_count": 6}, {"name": "Umbc", "match_count": 1}, {"name": "Umpqua Community College", "match_count": 28}, {"name": "Un Rostered", "match_count": 2}, {"name": "Una", "match_count": 2}, {"name": "Una-bcwc", "match_count": 4}, {"name": "Unaffiliated", "match_count": 152}, {"name": "Unaffiliated - COLLEGE", "match_count": 35}, {"name": "Unaffiliated - HS", "match_count": 24}, {"name": "Unaffiliated - UNATT", "match_count": 58}, {"name": "Unaffiliated HS", "match_count": 84}, {"name": "Unatt-nycrtc", "match_count": 2}, {"name": "Unatt-prtc", "match_count": 6}, {"name": "Unattached", "match_count": 1389}, {"name": "Unattached - Oregon State", "match_count": 1}, {"name": "Unattached - Unattached", "match_count": 41}, {"name": "Unattached Assins", "match_count": 2}, {"name": "Unattached CA", "match_count": 9}, {"name": "Unattached Montevallo", "match_count": 1}, {"name": "Unattached-", "match_count": 1}, {"name": "Unattached- Buffalo", "match_count": 43}, {"name": "Unattached- UPJ", "match_count": 12}, {"name": "Unattached-American", "match_count": 1}, {"name": "Unattached-ESU", "match_count": 1}, {"name": "Unattached-Long Island University", "match_count": 1}, {"name": "Unattached-UNA", "match_count": 1}, {"name": "Unattached-UPJ", "match_count": 5}, {"name": "Unattached-Unroster", "match_count": 23}, {"name": "Unattached-Unrostered", "match_count": 28}, {"name": "Unattatched", "match_count": 24}, {"name": "Unattended", "match_count": 2}, {"name": "Union College of Union County", "match_count": 1}, {"name": "Union County College", "match_count": 15}, {"name": "United Wrestling Katy", "match_count": 5}, {"name": "University At Albany", "match_count": 1}, {"name": "University Of Central Florida", "match_count": 120}, {"name": "University of Akron", "match_count": 14}, {"name": "University of Dubuque Wrestling club", "match_count": 2}, {"name": "University of Florida", "match_count": 14}, {"name": "University of Louisville", "match_count": 5}, {"name": "University of Massachusetts Amherst", "match_count": 9}, {"name": "University of North Texas", "match_count": 2}, {"name": "University of Northern Iowa", "match_count": 1}, {"name": "University of Oregon", "match_count": 1}, {"name": "University of Rio Grande", "match_count": 24}, {"name": "University of Saint Mary (KS)", "match_count": 22}, {"name": "University of Saskatchewan", "match_count": 18}, {"name": "University of Tennessee", "match_count": 1}, {"name": "University of Tennessee at Knoxville", "match_count": 5}, {"name": "University of Virginia", "match_count": 10}, {"name": "University of the Ozarks", "match_count": 51}, {"name": "Unnatched-UNATT", "match_count": 1}, {"name": "Unnattached", "match_count": 8}, {"name": "Unros", "match_count": 11}, {"name": "Unrostered", "match_count": 187}, {"name": "Unrostered - Angry Fish", "match_count": 1}, {"name": "Unrostered - D1 WC", "match_count": 3}, {"name": "Unrostered - EAP", "match_count": 11}, {"name": "Unrostered - Funky Monkey", "match_count": 9}, {"name": "Unrostered - Gladiator", "match_count": 4}, {"name": "Unrostered - Hutchy Hammers", "match_count": 3}, {"name": "Unrostered - KD Trained", "match_count": 3}, {"name": "Unrostered - Midwest Regional Training Center", "match_count": 6}, {"name": "Unrostered - NAWC", "match_count": 2}, {"name": "Unrostered - Orchard", "match_count": 3}, {"name": "Unrostered - Perrysburg", "match_count": 4}, {"name": "Unrostered - Spartan Combat RTC", "match_count": 21}, {"name": "Unrostered - UnAttached", "match_count": 25}, {"name": "Unrostered - United Training Facility", "match_count": 2}, {"name": "Unrostered - Young Guns / Hutchy Hammers", "match_count": 2}, {"name": "Unrostered Bull Trained", "match_count": 1}, {"name": "Unrostered Clarion", "match_count": 1}, {"name": "Unrostered NAPS", "match_count": 17}, {"name": "Unrostered- Boom Ranch", "match_count": 1}, {"name": "Unrostered- Brown", "match_count": 2}, {"name": "Unrostered- Compound", "match_count": 1}, {"name": "Unrostered- Duquesne", "match_count": 2}, {"name": "Unrostered- Harvard", "match_count": 4}, {"name": "Unrostered- NYCRTC", "match_count": 2}, {"name": "Unrostered- Orchard", "match_count": 2}, {"name": "Unrostered- PA Titans", "match_count": 3}, {"name": "Unrostered- Pitt Bull", "match_count": 2}, {"name": "Unrostered- Quest", "match_count": 1}, {"name": "Unrostered- Redbank Valley", "match_count": 1}, {"name": "Unrostered- Spartan Combat RTC", "match_count": 50}, {"name": "Unrostered- Spire", "match_count": 9}, {"name": "Unrostered- Stellar", "match_count": 7}, {"name": "Unrostered- Washington PA", "match_count": 3}, {"name": "Unrostered- Young Guns", "match_count": 4}, {"name": "Unrostered- Zephyrhills Christian", "match_count": 1}, {"name": "Unrostered-NLWC", "match_count": 5}, {"name": "Unrostered-Navy WC", "match_count": 12}, {"name": "Unrostered-Slippery Rock University", "match_count": 14}, {"name": "Unrostered-Spartan Combat RTC", "match_count": 61}, {"name": "Unrstered", "match_count": 4}, {"name": "UofM Club Wrestling", "match_count": 5}, {"name": "Upper Iowa", "match_count": 94}, {"name": "Ursinus", "match_count": 45}, {"name": "Usmaps", "match_count": 52}, {"name": "Utah Tech", "match_count": 1}, {"name": "Utah Tech.", "match_count": 1}, {"name": "Utah Technical University", "match_count": 1}, {"name": "Utah Valley", "match_count": 1988}, {"name": "Utica", "match_count": 3}, {"name": "VMI", "match_count": 1815}, {"name": "Vailant Prep", "match_count": 5}, {"name": "Valiant", "match_count": 2}, {"name": "Valiant College Prep", "match_count": 7}, {"name": "Valiant College Preparatory", "match_count": 6}, {"name": "Valiant Prep", "match_count": 24}, {"name": "Valiant Prep-UNATT", "match_count": 1}, {"name": "Vanguard", "match_count": 46}, {"name": "Vanguard University", "match_count": 65}, {"name": "Victor Valley College", "match_count": 21}, {"name": "Virginia", "match_count": 2180}, {"name": "Virginia Team Predator", "match_count": 10}, {"name": "Virginia Tech", "match_count": 2234}, {"name": "WCRTC", "match_count": 3}, {"name": "WVU Tech (W.Va.)", "match_count": 13}, {"name": "Wabash", "match_count": 151}, {"name": "Waldorf (Iowa)", "match_count": 13}, {"name": "Warner Pacific", "match_count": 3}, {"name": "Warrington", "match_count": 1}, {"name": "Wartburg", "match_count": 36}, {"name": "Washington & Lee", "match_count": 13}, {"name": "Washington State", "match_count": 8}, {"name": "Washington State University", "match_count": 6}, {"name": "Wayland Baptist (Texas)", "match_count": 29}, {"name": "Wayne State", "match_count": 2}, {"name": "Waynesboro", "match_count": 2}, {"name": "Waynesburg", "match_count": 13}, {"name": "West Chester University", "match_count": 1}, {"name": "West Liberty", "match_count": 109}, {"name": "West Point Prep", "match_count": 33}, {"name": "West Virginia", "match_count": 2918}, {"name": "Westcliff", "match_count": 14}, {"name": "Western Colorado", "match_count": 168}, {"name": "Western Michigan University", "match_count": 1}, {"name": "Western Washington University", "match_count": 3}, {"name": "Western Wyoming College", "match_count": 235}, {"name": "Westminster", "match_count": 15}, {"name": "Wheaton (IL)", "match_count": 4}, {"name": "Wheeling", "match_count": 36}, {"name": "Wilkes", "match_count": 113}, {"name": "William Jewell", "match_count": 7}, {"name": "William Jewell College", "match_count": 3}, {"name": "William Penn (Iowa)", "match_count": 24}, {"name": "William Woods University", "match_count": 7}, {"name": "Williams Baptist", "match_count": 11}, {"name": "Williams College", "match_count": 97}, {"name": "Wilmington", "match_count": 15}, {"name": "Winesburgh", "match_count": 1}, {"name": "Wisconsin", "match_count": 1974}, {"name": "Wisconsin-Eau Claire", "match_count": 81}, {"name": "Wisconsin-La Crosse", "match_count": 64}, {"name": "Wisconsin-Oshkosh", "match_count": 37}, {"name": "Wisconsin-Parkside", "match_count": 183}, {"name": "Wisconsin-Platteville", "match_count": 10}, {"name": "Wisconsin-Stevens Point", "match_count": 5}, {"name": "Wisconsin-Whitewater", "match_count": 93}, {"name": "Witchduck Training Center", "match_count": 3}, {"name": "Wpwc", "match_count": 9}, {"name": "Wrestling Club at ISU", "match_count": 1}, {"name": "Wrestling Club at WMU", "match_count": 1}, {"name": "Wright Wrestling Academy", "match_count": 2}, {"name": "Wyoming", "match_count": 2078}, {"name": "Wyoming SEM", "match_count": 1}, {"name": "Wyoming Seminary", "match_count": 6}, {"name": "Xavier", "match_count": 2}, {"name": "Xtreme Traning", "match_count": 1}, {"name": "Yale St", "match_count": 2}, {"name": "York (Neb.)", "match_count": 25}, {"name": "cbfw", "match_count": 1}, {"name": "cwc", "match_count": 4}, {"name": "glenville", "match_count": 11}, {"name": "grays harbor", "match_count": 7}, {"name": "jamestown community college", "match_count": 1}, {"name": "sacred heart", "match_count": 10}, {"name": "sertc", "match_count": 3}, {"name": "unattached", "match_count": 50}, {"name": "uww", "match_count": 1}]